Metadata-Version: 2.1
Name: wiggle2
Version: 0.2
Summary: Utility to plot seismic data, inspired by [wiggle](https://github.com/lijunzh/wiggle) function. I provide more options, such as orientation, normalization method, scale. 
Home-page: https://github.com/FrankLiu007/wiggle2
Author: liu qimin
Author-email: liuqimin2009@163.com
License: UNKNOWN
Platform: UNKNOWN
License-File: LICENSE
